daffy/__init__.py
daffy/checks.py
daffy/config.py
daffy/dataframe_types.py
daffy/decorators.py
daffy/narwhals_compat.py
daffy/patterns.py
daffy/py.typed
daffy/pydantic_types.py
daffy/row_validation.py
daffy/utils.py
daffy/validation.py
daffy-2.3.1.dist-info/METADATA
daffy-2.3.1.dist-info/WHEEL
daffy-2.3.1.dist-info/licenses/LICENSE
daffy-2.3.1.dist-info/RECORD
