Metadata-Version: 2.4
Name: daffy
Version: 2.3.1
Summary: Function decorators for DataFrame validation - columns, data types, and row-level validation with Pydantic. Supports Pandas, Polars, Modin, and PyArrow.
Project-URL: homepage, https://github.com/vertti/daffy
Project-URL: repository, https://github.com/vertti/daffy
Project-URL: documentation, https://github.com/vertti/daffy/blob/master/README.md
Project-URL: changelog, https://github.com/vertti/daffy/blob/master/CHANGELOG.md
Project-URL: issues, https://github.com/vertti/daffy/issues
Author-email: Janne Sinivirta <janne.sinivirta@gmail.com>
License-Expression: MIT
License-File: LICENSE
Keywords: column-validation,data-pipeline,data-quality,data-validation,dataframe,dataframe-schema,dataframe-validator,decorator,modin,narwhals,pandas,pandas-validation,polars,polars-validation,pyarrow,pydantic,row-validation,runtime-validation,schema,typing,validate-dataframe,validation
Classifier: Development Status :: 5 - Production/Stable
Classifier: Framework :: Pydantic
Classifier: Framework :: Pydantic :: 2
Classifier: Intended Audience :: Developers
Classifier: License :: OSI Approved :: MIT License
Classifier: Operating System :: OS Independent
Classifier: Programming Language :: Python :: 3
Classifier: Programming Language :: Python :: 3.10
Classifier: Programming Language :: Python :: 3.11
Classifier: Programming Language :: Python :: 3.12
Classifier: Programming Language :: Python :: 3.13
Classifier: Programming Language :: Python :: 3.14
Classifier: Topic :: Software Development :: Libraries :: Python Modules
Classifier: Topic :: Software Development :: Quality Assurance
Classifier: Topic :: Software Development :: Testing
Classifier: Typing :: Typed
Requires-Python: >=3.10
Requires-Dist: narwhals>=2.14.0
Requires-Dist: tomli>=2.0.0
